LICENSE
MANIFEST.in
README.md
description.rst
setup.cfg
setup.py
docs/index.md
portable_fdsnws_dataselect/__init__.py
portable_fdsnws_dataselect/handler.py
portable_fdsnws_dataselect/miniseed.py
portable_fdsnws_dataselect/msriterator.py
portable_fdsnws_dataselect/request.py
portable_fdsnws_dataselect/server.py
portable_fdsnws_dataselect/test.py
portable_fdsnws_dataselect.egg-info/PKG-INFO
portable_fdsnws_dataselect.egg-info/SOURCES.txt
portable_fdsnws_dataselect.egg-info/dependency_links.txt
portable_fdsnws_dataselect.egg-info/entry_points.txt
portable_fdsnws_dataselect.egg-info/top_level.txt
portable_fdsnws_dataselect/docs/application.wadl
portable_fdsnws_dataselect/docs/help.html
portable_fdsnws_dataselect/docs/index.html
portable_fdsnws_dataselect/docs/style.css
portable_fdsnws_dataselect/example/server.ini