Metadata-Version: 1.1
Name: portable-fdsnws-dataselect
Version: 1.2.0
Summary: A portable fdsnws-dataselect/1 server
Home-page: https://iris-edu.github.io/portable-fdsnws-dataselect/
Author: IRIS DMC
Author-email: software-owner@iris.washington.edu
License: LGPL 3.0
Keywords: FDSN webservice IRIS miniSEED
Platform: UNKNOWN
Classifier: Development Status :: 4 - Beta
Classifier: Environment :: Console
Classifier: Intended Audience :: Science/Research
Classifier: Intended Audience :: Information Technology
Classifier: Intended Audience :: System Administrators
Classifier: Topic :: Internet :: WWW/HTTP :: HTTP Servers
Classifier: Topic :: Scientific/Engineering :: Physics
Classifier: License :: OSI Approved :: GNU Lesser General Public License v3 (LGPLv3)
Classifier: Programming Language :: Python :: 2.7
Classifier: Programming Language :: Python :: 3.4
Classifier: Programming Language :: Python :: 3.5
Classifier: Programming Language :: Python :: 3.6
